GPT_Helper/__init__.py
GPT_Helper/client.py
GPT_Helper/exceptions.py
GPT_Helper/history.py
GPT_Helper/utils.py
gpt_helper-0.1.0.dist-info/METADATA
gpt_helper-0.1.0.dist-info/WHEEL
gpt_helper-0.1.0.dist-info/top_level.txt
gpt_helper-0.1.0.dist-info/RECORD
