Metadata-Version: 2.4
Name: GPT_Helper
Version: 0.1.0
Summary: A helper library for interacting with ChatGPT.
Author-email: KishoreM <kishor.mullappilly@gmail.com>
License: MIT
Requires-Python: >=3.8
Requires-Dist: openai>=1.0.0
